odoo/addons/pdf_xml_attachment/README.rst
odoo/addons/pdf_xml_attachment/__init__.py
odoo/addons/pdf_xml_attachment/__manifest__.py
odoo/addons/pdf_xml_attachment/utils.py
odoo/addons/pdf_xml_attachment/i18n/es.po
odoo/addons/pdf_xml_attachment/i18n/hr.po
odoo/addons/pdf_xml_attachment/i18n/it.po
odoo/addons/pdf_xml_attachment/i18n/pdf_helper.pot
odoo/addons/pdf_xml_attachment/i18n/pdf_xml_attachment.pot
odoo/addons/pdf_xml_attachment/models/__init__.py
odoo/addons/pdf_xml_attachment/models/helper.py
odoo/addons/pdf_xml_attachment/readme/CONTRIBUTORS.md
odoo/addons/pdf_xml_attachment/readme/DESCRIPTION.md
odoo/addons/pdf_xml_attachment/readme/USAGE.md
odoo/addons/pdf_xml_attachment/static/description/icon.png
odoo/addons/pdf_xml_attachment/static/description/index.html
odoo/addons/pdf_xml_attachment/tests/__init__.py
odoo/addons/pdf_xml_attachment/tests/test_helper.py
odoo/addons/pdf_xml_attachment/tests/fixtures/pdf_with_xml_test.pdf
odoo_addon_pdf_xml_attachment-18.0.1.0.0.2.dist-info/METADATA
odoo_addon_pdf_xml_attachment-18.0.1.0.0.2.dist-info/WHEEL
odoo_addon_pdf_xml_attachment-18.0.1.0.0.2.dist-info/top_level.txt
odoo_addon_pdf_xml_attachment-18.0.1.0.0.2.dist-info/RECORD
